match_tokens_py/__init__.py
match_tokens_py/sendgrid.py
match_tokens_py/twilio.py
match_tokens_py-1.0.0.dist-info/LICENSE.txt
match_tokens_py-1.0.0.dist-info/METADATA
match_tokens_py-1.0.0.dist-info/WHEEL
match_tokens_py-1.0.0.dist-info/top_level.txt
match_tokens_py-1.0.0.dist-info/RECORD
