Metadata-Version: 2.1
Name: match-tokens-py
Version: 1.0.0
Summary: Match token library for Python
Home-page: https://match.twilio.design
Author: Twilio Inc.
Author-email: match@twilio.com
License: UNKNOWN
Platform: UNKNOWN
Classifier: License :: Other/Proprietary License
Classifier: Operating System :: OS Independent
Classifier: Programming Language :: Python :: 3
License-File: LICENSE.txt
